demo/__init__.py
demo/pub.py
demo/run.py
demo/page/__init__.py
demo/page/web_page.py
demo/pages/__init__.py
demo/pages/demo_page.py
demo/pages/web_page.py
demo/tests/__init__.py
demo/tests/test_demo1.py
demo/tests/test_para.py
demo/tests/test_web.py
testweb/__init__.py
testweb/case.py
testweb/cli.py
testweb/page.py
testweb/scaffold.py
testweb/core/__init__.py
testweb/core/api/__init__.py
testweb/core/api/request.py
testweb/core/web/__init__.py
testweb/core/web/driver.py
testweb/core/web/element.py
testweb/running/__init__.py
testweb/running/conf.yml
testweb/running/runner.py
testweb/testdata/__init__.py
testweb/testdata/data.py
testweb/utils/__init__.py
testweb/utils/allure_util.py
testweb/utils/common.py
testweb/utils/config.py
testweb/utils/des_util.py
testweb/utils/dingtalk.py
testweb/utils/excel.py
testweb/utils/exceptions.py
testweb/utils/log.py
testweb/utils/mail.py
testweb/utils/mysql_util.py
testweb/utils/pytest_util.py
testweb/utils/swagger_util.py
testweb-0.1.3.dist-info/METADATA
testweb-0.1.3.dist-info/WHEEL
testweb-0.1.3.dist-info/entry_points.txt
testweb-0.1.3.dist-info/top_level.txt
testweb-0.1.3.dist-info/RECORD
